mazerunner/exceptions.py
mazerunner/api_client.py
mazerunner/__init__.py
mazerunner/samples/elasticsearch_responder_monitor.py
mazerunner/samples/assign_group_to_cidr.py
mazerunner/samples/delete_everything.py
mazerunner/samples/create_smb_breadcrumbs.py
mazerunner/samples/deploy_to_linux.py
mazerunner/samples/create_deployment_group_with_all_breadcrumb_types.py
mazerunner/samples/syslog_server_active_soc_reporter.py
mazerunner/samples/track_live_alerts.py
mazerunner/samples/__init__.py
disable_maze/exceptions.py
disable_maze/api_client.py
disable_maze/__init__.py
disable_maze/samples/elasticsearch_responder_monitor.py
disable_maze/samples/assign_group_to_cidr.py
disable_maze/samples/delete_everything.py
disable_maze/samples/create_smb_breadcrumbs.py
disable_maze/samples/deploy_to_linux.py
disable_maze/samples/create_deployment_group_with_all_breadcrumb_types.py
disable_maze/samples/syslog_server_active_soc_reporter.py
disable_maze/samples/track_live_alerts.py
disable_maze/samples/__init__.py
mazerunner_sdk-1.1.3.dist-info/RECORD
mazerunner_sdk-1.1.3.dist-info/WHEEL
mazerunner_sdk-1.1.3.dist-info/METADATA
mazerunner_sdk-1.1.3.dist-info/top_level.txt
mazerunner_sdk-1.1.3.dist-info/metadata.json
mazerunner_sdk-1.1.3.dist-info/DESCRIPTION.rst
