Metadata-Version: 2.0
Name: mazerunner-sdk
Version: 1.1.3
Summary: MazeRunner SDK
Home-page: https://github.com/Cymmetria/mazerunner_sdk_python
Author: Cymmetria
Author-email: publicapi@cymmetria.com
License: BSD 3-Clause
Download-URL: https://github.com/Cymmetria/mazerunner_sdk_python/tarball/1.1.3
Keywords: cymmetria,mazerunner,sdk,api
Platform: UNKNOWN
Requires-Dist: argparse (==1.2.1)
Requires-Dist: mohawk (==0.3.4)
Requires-Dist: requests (==2.13.0)
Requires-Dist: requests-hawk (==1.0.0)
Requires-Dist: six (==1.10.0)
Requires-Dist: wsgiref (==0.1.2)
